{
  "translation": "deck.charta.fun_neon",
  "suits": [
    {
      "suit": "charta:red",
      "texture": "charta:fun_neon/red",
      "translation": "suit.charta.red"
    },
    {
      "suit": "charta:yellow",
      "texture": "charta:fun_neon/yellow",
      "translation": "suit.charta.yellow"
    },
    {
      "suit": "charta:green",
      "texture": "charta:fun_neon/green",
      "translation": "suit.charta.green"
    },
    {
      "suit": "charta:blue",
      "texture": "charta:fun_neon/blue",
      "translation": "suit.charta.blue"
    }
  ],
  "cards": [
    {
      "card": {
        "components": {
          "charta:suit": "charta:green",
          "charta:rank": "charta:wild",
          "charta:flipped": false
        }
      },
      "texture": "charta:fun_neon/green_wild",
      "translation": "card.charta.wild"
    },
    {
      "card": {
        "components": {
          "charta:suit": "charta:green",
          "charta:rank": "charta:zero",
          "charta:flipped": false
        }
      },
      "texture": "charta:fun_neon/green_zero",
      "translation": "card.charta.green.zero"
    },
    {
      "card": {
        "components": {
          "charta:suit": "charta:green",
          "charta:rank": "charta:ace",
          "charta:flipped": false
        }
      },
      "texture": "charta:fun_neon/green_one",
      "translation": "card.charta.green.one"
    },
    {
      "card": {
        "components": {
          "charta:suit": "charta:green",
          "charta:rank": "charta:ace",
          "charta:flipped": false
        }
      },
      "texture": "charta:fun_neon/green_one",
      "translation": "card.charta.green.one"
    },
    {
      "card": {
        "components": {
          "charta:suit": "charta:green",
          "charta:rank": "charta:two",
          "charta:flipped": false
        }
      },
      "texture": "charta:fun_neon/green_two",
      "translation": "card.charta.green.two"
    },
    {
      "card": {
        "components": {
          "charta:suit": "charta:green",
          "charta:rank": "charta:two",
          "charta:flipped": false
        }
      },
      "texture": "charta:fun_neon/green_two",
      "translation": "card.charta.green.two"
    },
    {
      "card": {
        "components": {
          "charta:suit": "charta:green",
          "charta:rank": "charta:three",
          "charta:flipped": false
        }
      },
      "texture": "charta:fun_neon/green_three",
      "translation": "card.charta.green.three"
    },
    {
      "card": {
        "components": {
          "charta:suit": "charta:green",
          "charta:rank": "charta:three",
          "charta:flipped": false
        }
      },
      "texture": "charta:fun_neon/green_three",
      "translation": "card.charta.green.three"
    },
    {
      "card": {
        "components": {
          "charta:suit": "charta:green",
          "charta:rank": "charta:four",
          "charta:flipped": false
        }
      },
      "texture": "charta:fun_neon/green_four",
      "translation": "card.charta.green.four"
    },
    {
      "card": {
        "components": {
          "charta:suit": "charta:green",
          "charta:rank": "charta:four",
          "charta:flipped": false
        }
      },
      "texture": "charta:fun_neon/green_four",
      "translation": "card.charta.green.four"
    },
    {
      "card": {
        "components": {
          "charta:suit": "charta:green",
          "charta:rank": "charta:five",
          "charta:flipped": false
        }
      },
      "texture": "charta:fun_neon/green_five",
      "translation": "card.charta.green.five"
    },
    {
      "card": {
        "components": {
          "charta:suit": "charta:green",
          "charta:rank": "charta:five",
          "charta:flipped": false
        }
      },
      "texture": "charta:fun_neon/green_five",
      "translation": "card.charta.green.five"
    },
    {
      "card": {
        "components": {
          "charta:suit": "charta:green",
          "charta:rank": "charta:six",
          "charta:flipped": false
        }
      },
      "texture": "charta:fun_neon/green_six",
      "translation": "card.charta.green.six"
    },
    {
      "card": {
        "components": {
          "charta:suit": "charta:green",
          "charta:rank": "charta:six",
          "charta:flipped": false
        }
      },
      "texture": "charta:fun_neon/green_six",
      "translation": "card.charta.green.six"
    },
    {
      "card": {
        "components": {
          "charta:suit": "charta:green",
          "charta:rank": "charta:seven",
          "charta:flipped": false
        }
      },
      "texture": "charta:fun_neon/green_seven",
      "translation": "card.charta.green.seven"
    },
    {
      "card": {
        "components": {
          "charta:suit": "charta:green",
          "charta:rank": "charta:seven",
          "charta:flipped": false
        }
      },
      "texture": "charta:fun_neon/green_seven",
      "translation": "card.charta.green.seven"
    },
    {
      "card": {
        "components": {
          "charta:suit": "charta:green",
          "charta:rank": "charta:eight",
          "charta:flipped": false
        }
      },
      "texture": "charta:fun_neon/green_eight",
      "translation": "card.charta.green.eight"
    },
    {
      "card": {
        "components": {
          "charta:suit": "charta:green",
          "charta:rank": "charta:eight",
          "charta:flipped": false
        }
      },
      "texture": "charta:fun_neon/green_eight",
      "translation": "card.charta.green.eight"
    },
    {
      "card": {
        "components": {
          "charta:suit": "charta:green",
          "charta:rank": "charta:nine",
          "charta:flipped": false
        }
      },
      "texture": "charta:fun_neon/green_nine",
      "translation": "card.charta.green.nine"
    },
    {
      "card": {
        "components": {
          "charta:suit": "charta:green",
          "charta:rank": "charta:nine",
          "charta:flipped": false
        }
      },
      "texture": "charta:fun_neon/green_nine",
      "translation": "card.charta.green.nine"
    },
    {
      "card": {
        "components": {
          "charta:suit": "charta:green",
          "charta:rank": "charta:ten",
          "charta:flipped": false
        }
      },
      "texture": "charta:fun_neon/green_block",
      "translation": "card.charta.green.block"
    },
    {
      "card": {
        "components": {
          "charta:suit": "charta:green",
          "charta:rank": "charta:ten",
          "charta:flipped": false
        }
      },
      "texture": "charta:fun_neon/green_block",
      "translation": "card.charta.green.block"
    },
    {
      "card": {
        "components": {
          "charta:suit": "charta:green",
          "charta:rank": "charta:jack",
          "charta:flipped": false
        }
      },
      "texture": "charta:fun_neon/green_reverse",
      "translation": "card.charta.green.reverse"
    },
    {
      "card": {
        "components": {
          "charta:suit": "charta:green",
          "charta:rank": "charta:jack",
          "charta:flipped": false
        }
      },
      "texture": "charta:fun_neon/green_reverse",
      "translation": "card.charta.green.reverse"
    },
    {
      "card": {
        "components": {
          "charta:suit": "charta:green",
          "charta:rank": "charta:king",
          "charta:flipped": false
        }
      },
      "texture": "charta:fun_neon/green_plustwo",
      "translation": "card.charta.green.plustwo"
    },
    {
      "card": {
        "components": {
          "charta:suit": "charta:green",
          "charta:rank": "charta:king",
          "charta:flipped": false
        }
      },
      "texture": "charta:fun_neon/green_plustwo",
      "translation": "card.charta.green.plustwo"
    },
    {
      "card": {
        "components": {
          "charta:suit": "charta:green",
          "charta:rank": "charta:wildplusfour",
          "charta:flipped": false
        }
      },
      "texture": "charta:fun_neon/green_wildplusfour",
      "translation": "card.charta.wildplusfour"
    },
    {
      "card": {
        "components": {
          "charta:suit": "charta:red",
          "charta:rank": "charta:wild",
          "charta:flipped": false
        }
      },
      "texture": "charta:fun_neon/red_wild",
      "translation": "card.charta.wild"
    },
    {
      "card": {
        "components": {
          "charta:suit": "charta:red",
          "charta:rank": "charta:zero",
          "charta:flipped": false
        }
      },
      "texture": "charta:fun_neon/red_zero",
      "translation": "card.charta.red.zero"
    },
    {
      "card": {
        "components": {
          "charta:suit": "charta:red",
          "charta:rank": "charta:ace",
          "charta:flipped": false
        }
      },
      "texture": "charta:fun_neon/red_one",
      "translation": "card.charta.red.one"
    },
    {
      "card": {
        "components": {
          "charta:suit": "charta:red",
          "charta:rank": "charta:ace",
          "charta:flipped": false
        }
      },
      "texture": "charta:fun_neon/red_one",
      "translation": "card.charta.red.one"
    },
    {
      "card": {
        "components": {
          "charta:suit": "charta:red",
          "charta:rank": "charta:two",
          "charta:flipped": false
        }
      },
      "texture": "charta:fun_neon/red_two",
      "translation": "card.charta.red.two"
    },
    {
      "card": {
        "components": {
          "charta:suit": "charta:red",
          "charta:rank": "charta:two",
          "charta:flipped": false
        }
      },
      "texture": "charta:fun_neon/red_two",
      "translation": "card.charta.red.two"
    },
    {
      "card": {
        "components": {
          "charta:suit": "charta:red",
          "charta:rank": "charta:three",
          "charta:flipped": false
        }
      },
      "texture": "charta:fun_neon/red_three",
      "translation": "card.charta.red.three"
    },
    {
      "card": {
        "components": {
          "charta:suit": "charta:red",
          "charta:rank": "charta:three",
          "charta:flipped": false
        }
      },
      "texture": "charta:fun_neon/red_three",
      "translation": "card.charta.red.three"
    },
    {
      "card": {
        "components": {
          "charta:suit": "charta:red",
          "charta:rank": "charta:four",
          "charta:flipped": false
        }
      },
      "texture": "charta:fun_neon/red_four",
      "translation": "card.charta.red.four"
    },
    {
      "card": {
        "components": {
          "charta:suit": "charta:red",
          "charta:rank": "charta:four",
          "charta:flipped": false
        }
      },
      "texture": "charta:fun_neon/red_four",
      "translation": "card.charta.red.four"
    },
    {
      "card": {
        "components": {
          "charta:suit": "charta:red",
          "charta:rank": "charta:five",
          "charta:flipped": false
        }
      },
      "texture": "charta:fun_neon/red_five",
      "translation": "card.charta.red.five"
    },
    {
      "card": {
        "components": {
          "charta:suit": "charta:red",
          "charta:rank": "charta:five",
          "charta:flipped": false
        }
      },
      "texture": "charta:fun_neon/red_five",
      "translation": "card.charta.red.five"
    },
    {
      "card": {
        "components": {
          "charta:suit": "charta:red",
          "charta:rank": "charta:six",
          "charta:flipped": false
        }
      },
      "texture": "charta:fun_neon/red_six",
      "translation": "card.charta.red.six"
    },
    {
      "card": {
        "components": {
          "charta:suit": "charta:red",
          "charta:rank": "charta:six",
          "charta:flipped": false
        }
      },
      "texture": "charta:fun_neon/red_six",
      "translation": "card.charta.red.six"
    },
    {
      "card": {
        "components": {
          "charta:suit": "charta:red",
          "charta:rank": "charta:seven",
          "charta:flipped": false
        }
      },
      "texture": "charta:fun_neon/red_seven",
      "translation": "card.charta.red.seven"
    },
    {
      "card": {
        "components": {
          "charta:suit": "charta:red",
          "charta:rank": "charta:seven",
          "charta:flipped": false
        }
      },
      "texture": "charta:fun_neon/red_seven",
      "translation": "card.charta.red.seven"
    },
    {
      "card": {
        "components": {
          "charta:suit": "charta:red",
          "charta:rank": "charta:eight",
          "charta:flipped": false
        }
      },
      "texture": "charta:fun_neon/red_eight",
      "translation": "card.charta.red.eight"
    },
    {
      "card": {
        "components": {
          "charta:suit": "charta:red",
          "charta:rank": "charta:eight",
          "charta:flipped": false
        }
      },
      "texture": "charta:fun_neon/red_eight",
      "translation": "card.charta.red.eight"
    },
    {
      "card": {
        "components": {
          "charta:suit": "charta:red",
          "charta:rank": "charta:nine",
          "charta:flipped": false
        }
      },
      "texture": "charta:fun_neon/red_nine",
      "translation": "card.charta.red.nine"
    },
    {
      "card": {
        "components": {
          "charta:suit": "charta:red",
          "charta:rank": "charta:nine",
          "charta:flipped": false
        }
      },
      "texture": "charta:fun_neon/red_nine",
      "translation": "card.charta.red.nine"
    },
    {
      "card": {
        "components": {
          "charta:suit": "charta:red",
          "charta:rank": "charta:ten",
          "charta:flipped": false
        }
      },
      "texture": "charta:fun_neon/red_block",
      "translation": "card.charta.red.block"
    },
    {
      "card": {
        "components": {
          "charta:suit": "charta:red",
          "charta:rank": "charta:ten",
          "charta:flipped": false
        }
      },
      "texture": "charta:fun_neon/red_block",
      "translation": "card.charta.red.block"
    },
    {
      "card": {
        "components": {
          "charta:suit": "charta:red",
          "charta:rank": "charta:jack",
          "charta:flipped": false
        }
      },
      "texture": "charta:fun_neon/red_reverse",
      "translation": "card.charta.red.reverse"
    },
    {
      "card": {
        "components": {
          "charta:suit": "charta:red",
          "charta:rank": "charta:jack",
          "charta:flipped": false
        }
      },
      "texture": "charta:fun_neon/red_reverse",
      "translation": "card.charta.red.reverse"
    },
    {
      "card": {
        "components": {
          "charta:suit": "charta:red",
          "charta:rank": "charta:king",
          "charta:flipped": false
        }
      },
      "texture": "charta:fun_neon/red_plustwo",
      "translation": "card.charta.red.plustwo"
    },
    {
      "card": {
        "components": {
          "charta:suit": "charta:red",
          "charta:rank": "charta:king",
          "charta:flipped": false
        }
      },
      "texture": "charta:fun_neon/red_plustwo",
      "translation": "card.charta.red.plustwo"
    },
    {
      "card": {
        "components": {
          "charta:suit": "charta:red",
          "charta:rank": "charta:wildplusfour",
          "charta:flipped": false
        }
      },
      "texture": "charta:fun_neon/red_wildplusfour",
      "translation": "card.charta.wildplusfour"
    },
    {
      "card": {
        "components": {
          "charta:suit": "charta:yellow",
          "charta:rank": "charta:wild",
          "charta:flipped": false
        }
      },
      "texture": "charta:fun_neon/yellow_wild",
      "translation": "card.charta.wild"
    },
    {
      "card": {
        "components": {
          "charta:suit": "charta:yellow",
          "charta:rank": "charta:zero",
          "charta:flipped": false
        }
      },
      "texture": "charta:fun_neon/yellow_zero",
      "translation": "card.charta.yellow.zero"
    },
    {
      "card": {
        "components": {
          "charta:suit": "charta:yellow",
          "charta:rank": "charta:ace",
          "charta:flipped": false
        }
      },
      "texture": "charta:fun_neon/yellow_one",
      "translation": "card.charta.yellow.one"
    },
    {
      "card": {
        "components": {
          "charta:suit": "charta:yellow",
          "charta:rank": "charta:ace",
          "charta:flipped": false
        }
      },
      "texture": "charta:fun_neon/yellow_one",
      "translation": "card.charta.yellow.one"
    },
    {
      "card": {
        "components": {
          "charta:suit": "charta:yellow",
          "charta:rank": "charta:two",
          "charta:flipped": false
        }
      },
      "texture": "charta:fun_neon/yellow_two",
      "translation": "card.charta.yellow.two"
    },
    {
      "card": {
        "components": {
          "charta:suit": "charta:yellow",
          "charta:rank": "charta:two",
          "charta:flipped": false
        }
      },
      "texture": "charta:fun_neon/yellow_two",
      "translation": "card.charta.yellow.two"
    },
    {
      "card": {
        "components": {
          "charta:suit": "charta:yellow",
          "charta:rank": "charta:three",
          "charta:flipped": false
        }
      },
      "texture": "charta:fun_neon/yellow_three",
      "translation": "card.charta.yellow.three"
    },
    {
      "card": {
        "components": {
          "charta:suit": "charta:yellow",
          "charta:rank": "charta:three",
          "charta:flipped": false
        }
      },
      "texture": "charta:fun_neon/yellow_three",
      "translation": "card.charta.yellow.three"
    },
    {
      "card": {
        "components": {
          "charta:suit": "charta:yellow",
          "charta:rank": "charta:four",
          "charta:flipped": false
        }
      },
      "texture": "charta:fun_neon/yellow_four",
      "translation": "card.charta.yellow.four"
    },
    {
      "card": {
        "components": {
          "charta:suit": "charta:yellow",
          "charta:rank": "charta:four",
          "charta:flipped": false
        }
      },
      "texture": "charta:fun_neon/yellow_four",
      "translation": "card.charta.yellow.four"
    },
    {
      "card": {
        "components": {
          "charta:suit": "charta:yellow",
          "charta:rank": "charta:five",
          "charta:flipped": false
        }
      },
      "texture": "charta:fun_neon/yellow_five",
      "translation": "card.charta.yellow.five"
    },
    {
      "card": {
        "components": {
          "charta:suit": "charta:yellow",
          "charta:rank": "charta:five",
          "charta:flipped": false
        }
      },
      "texture": "charta:fun_neon/yellow_five",
      "translation": "card.charta.yellow.five"
    },
    {
      "card": {
        "components": {
          "charta:suit": "charta:yellow",
          "charta:rank": "charta:six",
          "charta:flipped": false
        }
      },
      "texture": "charta:fun_neon/yellow_six",
      "translation": "card.charta.yellow.six"
    },
    {
      "card": {
        "components": {
          "charta:suit": "charta:yellow",
          "charta:rank": "charta:six",
          "charta:flipped": false
        }
      },
      "texture": "charta:fun_neon/yellow_six",
      "translation": "card.charta.yellow.six"
    },
    {
      "card": {
        "components": {
          "charta:suit": "charta:yellow",
          "charta:rank": "charta:seven",
          "charta:flipped": false
        }
      },
      "texture": "charta:fun_neon/yellow_seven",
      "translation": "card.charta.yellow.seven"
    },
    {
      "card": {
        "components": {
          "charta:suit": "charta:yellow",
          "charta:rank": "charta:seven",
          "charta:flipped": false
        }
      },
      "texture": "charta:fun_neon/yellow_seven",
      "translation": "card.charta.yellow.seven"
    },
    {
      "card": {
        "components": {
          "charta:suit": "charta:yellow",
          "charta:rank": "charta:eight",
          "charta:flipped": false
        }
      },
      "texture": "charta:fun_neon/yellow_eight",
      "translation": "card.charta.yellow.eight"
    },
    {
      "card": {
        "components": {
          "charta:suit": "charta:yellow",
          "charta:rank": "charta:eight",
          "charta:flipped": false
        }
      },
      "texture": "charta:fun_neon/yellow_eight",
      "translation": "card.charta.yellow.eight"
    },
    {
      "card": {
        "components": {
          "charta:suit": "charta:yellow",
          "charta:rank": "charta:nine",
          "charta:flipped": false
        }
      },
      "texture": "charta:fun_neon/yellow_nine",
      "translation": "card.charta.yellow.nine"
    },
    {
      "card": {
        "components": {
          "charta:suit": "charta:yellow",
          "charta:rank": "charta:nine",
          "charta:flipped": false
        }
      },
      "texture": "charta:fun_neon/yellow_nine",
      "translation": "card.charta.yellow.nine"
    },
    {
      "card": {
        "components": {
          "charta:suit": "charta:yellow",
          "charta:rank": "charta:ten",
          "charta:flipped": false
        }
      },
      "texture": "charta:fun_neon/yellow_block",
      "translation": "card.charta.yellow.block"
    },
    {
      "card": {
        "components": {
          "charta:suit": "charta:yellow",
          "charta:rank": "charta:ten",
          "charta:flipped": false
        }
      },
      "texture": "charta:fun_neon/yellow_block",
      "translation": "card.charta.yellow.block"
    },
    {
      "card": {
        "components": {
          "charta:suit": "charta:yellow",
          "charta:rank": "charta:jack",
          "charta:flipped": false
        }
      },
      "texture": "charta:fun_neon/yellow_reverse",
      "translation": "card.charta.yellow.reverse"
    },
    {
      "card": {
        "components": {
          "charta:suit": "charta:yellow",
          "charta:rank": "charta:jack",
          "charta:flipped": false
        }
      },
      "texture": "charta:fun_neon/yellow_reverse",
      "translation": "card.charta.yellow.reverse"
    },
    {
      "card": {
        "components": {
          "charta:suit": "charta:yellow",
          "charta:rank": "charta:king",
          "charta:flipped": false
        }
      },
      "texture": "charta:fun_neon/yellow_plustwo",
      "translation": "card.charta.yellow.plustwo"
    },
    {
      "card": {
        "components": {
          "charta:suit": "charta:yellow",
          "charta:rank": "charta:king",
          "charta:flipped": false
        }
      },
      "texture": "charta:fun_neon/yellow_plustwo",
      "translation": "card.charta.yellow.plustwo"
    },
    {
      "card": {
        "components": {
          "charta:suit": "charta:yellow",
          "charta:rank": "charta:wildplusfour",
          "charta:flipped": false
        }
      },
      "texture": "charta:fun_neon/yellow_wildplusfour",
      "translation": "card.charta.wildplusfour"
    },
    {
      "card": {
        "components": {
          "charta:suit": "charta:blue",
          "charta:rank": "charta:wild",
          "charta:flipped": false
        }
      },
      "texture": "charta:fun_neon/blue_wild",
      "translation": "card.charta.wild"
    },
    {
      "card": {
        "components": {
          "charta:suit": "charta:blue",
          "charta:rank": "charta:zero",
          "charta:flipped": false
        }
      },
      "texture": "charta:fun_neon/blue_zero",
      "translation": "card.charta.blue.zero"
    },
    {
      "card": {
        "components": {
          "charta:suit": "charta:blue",
          "charta:rank": "charta:ace",
          "charta:flipped": false
        }
      },
      "texture": "charta:fun_neon/blue_one",
      "translation": "card.charta.blue.one"
    },
    {
      "card": {
        "components": {
          "charta:suit": "charta:blue",
          "charta:rank": "charta:ace",
          "charta:flipped": false
        }
      },
      "texture": "charta:fun_neon/blue_one",
      "translation": "card.charta.blue.one"
    },
    {
      "card": {
        "components": {
          "charta:suit": "charta:blue",
          "charta:rank": "charta:two",
          "charta:flipped": false
        }
      },
      "texture": "charta:fun_neon/blue_two",
      "translation": "card.charta.blue.two"
    },
    {
      "card": {
        "components": {
          "charta:suit": "charta:blue",
          "charta:rank": "charta:two",
          "charta:flipped": false
        }
      },
      "texture": "charta:fun_neon/blue_two",
      "translation": "card.charta.blue.two"
    },
    {
      "card": {
        "components": {
          "charta:suit": "charta:blue",
          "charta:rank": "charta:three",
          "charta:flipped": false
        }
      },
      "texture": "charta:fun_neon/blue_three",
      "translation": "card.charta.blue.three"
    },
    {
      "card": {
        "components": {
          "charta:suit": "charta:blue",
          "charta:rank": "charta:three",
          "charta:flipped": false
        }
      },
      "texture": "charta:fun_neon/blue_three",
      "translation": "card.charta.blue.three"
    },
    {
      "card": {
        "components": {
          "charta:suit": "charta:blue",
          "charta:rank": "charta:four",
          "charta:flipped": false
        }
      },
      "texture": "charta:fun_neon/blue_four",
      "translation": "card.charta.blue.four"
    },
    {
      "card": {
        "components": {
          "charta:suit": "charta:blue",
          "charta:rank": "charta:four",
          "charta:flipped": false
        }
      },
      "texture": "charta:fun_neon/blue_four",
      "translation": "card.charta.blue.four"
    },
    {
      "card": {
        "components": {
          "charta:suit": "charta:blue",
          "charta:rank": "charta:five",
          "charta:flipped": false
        }
      },
      "texture": "charta:fun_neon/blue_five",
      "translation": "card.charta.blue.five"
    },
    {
      "card": {
        "components": {
          "charta:suit": "charta:blue",
          "charta:rank": "charta:five",
          "charta:flipped": false
        }
      },
      "texture": "charta:fun_neon/blue_five",
      "translation": "card.charta.blue.five"
    },
    {
      "card": {
        "components": {
          "charta:suit": "charta:blue",
          "charta:rank": "charta:six",
          "charta:flipped": false
        }
      },
      "texture": "charta:fun_neon/blue_six",
      "translation": "card.charta.blue.six"
    },
    {
      "card": {
        "components": {
          "charta:suit": "charta:blue",
          "charta:rank": "charta:six",
          "charta:flipped": false
        }
      },
      "texture": "charta:fun_neon/blue_six",
      "translation": "card.charta.blue.six"
    },
    {
      "card": {
        "components": {
          "charta:suit": "charta:blue",
          "charta:rank": "charta:seven",
          "charta:flipped": false
        }
      },
      "texture": "charta:fun_neon/blue_seven",
      "translation": "card.charta.blue.seven"
    },
    {
      "card": {
        "components": {
          "charta:suit": "charta:blue",
          "charta:rank": "charta:seven",
          "charta:flipped": false
        }
      },
      "texture": "charta:fun_neon/blue_seven",
      "translation": "card.charta.blue.seven"
    },
    {
      "card": {
        "components": {
          "charta:suit": "charta:blue",
          "charta:rank": "charta:eight",
          "charta:flipped": false
        }
      },
      "texture": "charta:fun_neon/blue_eight",
      "translation": "card.charta.blue.eight"
    },
    {
      "card": {
        "components": {
          "charta:suit": "charta:blue",
          "charta:rank": "charta:eight",
          "charta:flipped": false
        }
      },
      "texture": "charta:fun_neon/blue_eight",
      "translation": "card.charta.blue.eight"
    },
    {
      "card": {
        "components": {
          "charta:suit": "charta:blue",
          "charta:rank": "charta:nine",
          "charta:flipped": false
        }
      },
      "texture": "charta:fun_neon/blue_nine",
      "translation": "card.charta.blue.nine"
    },
    {
      "card": {
        "components": {
          "charta:suit": "charta:blue",
          "charta:rank": "charta:nine",
          "charta:flipped": false
        }
      },
      "texture": "charta:fun_neon/blue_nine",
      "translation": "card.charta.blue.nine"
    },
    {
      "card": {
        "components": {
          "charta:suit": "charta:blue",
          "charta:rank": "charta:ten",
          "charta:flipped": false
        }
      },
      "texture": "charta:fun_neon/blue_block",
      "translation": "card.charta.blue.block"
    },
    {
      "card": {
        "components": {
          "charta:suit": "charta:blue",
          "charta:rank": "charta:ten",
          "charta:flipped": false
        }
      },
      "texture": "charta:fun_neon/blue_block",
      "translation": "card.charta.blue.block"
    },
    {
      "card": {
        "components": {
          "charta:suit": "charta:blue",
          "charta:rank": "charta:jack",
          "charta:flipped": false
        }
      },
      "texture": "charta:fun_neon/blue_reverse",
      "translation": "card.charta.blue.reverse"
    },
    {
      "card": {
        "components": {
          "charta:suit": "charta:blue",
          "charta:rank": "charta:jack",
          "charta:flipped": false
        }
      },
      "texture": "charta:fun_neon/blue_reverse",
      "translation": "card.charta.blue.reverse"
    },
    {
      "card": {
        "components": {
          "charta:suit": "charta:blue",
          "charta:rank": "charta:king",
          "charta:flipped": false
        }
      },
      "texture": "charta:fun_neon/blue_plustwo",
      "translation": "card.charta.blue.plustwo"
    },
    {
      "card": {
        "components": {
          "charta:suit": "charta:blue",
          "charta:rank": "charta:king",
          "charta:flipped": false
        }
      },
      "texture": "charta:fun_neon/blue_plustwo",
      "translation": "card.charta.blue.plustwo"
    },
    {
      "card": {
        "components": {
          "charta:suit": "charta:blue",
          "charta:rank": "charta:wildplusfour",
          "charta:flipped": false
        }
      },
      "texture": "charta:fun_neon/blue_wildplusfour",
      "translation": "card.charta.wildplusfour"
    }
  ],
  "rarity": "rare",
  "tradeable": false,
  "texture": "charta:fun_neon"
}